odoo/addons/project_task_send_by_mail/README.rst
odoo/addons/project_task_send_by_mail/__init__.py
odoo/addons/project_task_send_by_mail/__manifest__.py
odoo/addons/project_task_send_by_mail/data/task_template.xml
odoo/addons/project_task_send_by_mail/i18n/ar.po
odoo/addons/project_task_send_by_mail/i18n/ca.po
odoo/addons/project_task_send_by_mail/i18n/de.po
odoo/addons/project_task_send_by_mail/i18n/el.po
odoo/addons/project_task_send_by_mail/i18n/es.po
odoo/addons/project_task_send_by_mail/i18n/es_CR.po
odoo/addons/project_task_send_by_mail/i18n/es_MX.po
odoo/addons/project_task_send_by_mail/i18n/es_VE.po
odoo/addons/project_task_send_by_mail/i18n/fi.po
odoo/addons/project_task_send_by_mail/i18n/fr.po
odoo/addons/project_task_send_by_mail/i18n/gl.po
odoo/addons/project_task_send_by_mail/i18n/hr.po
odoo/addons/project_task_send_by_mail/i18n/hr_HR.po
odoo/addons/project_task_send_by_mail/i18n/hu.po
odoo/addons/project_task_send_by_mail/i18n/it.po
odoo/addons/project_task_send_by_mail/i18n/ja.po
odoo/addons/project_task_send_by_mail/i18n/lt.po
odoo/addons/project_task_send_by_mail/i18n/lv.po
odoo/addons/project_task_send_by_mail/i18n/mk.po
odoo/addons/project_task_send_by_mail/i18n/mn.po
odoo/addons/project_task_send_by_mail/i18n/nl.po
odoo/addons/project_task_send_by_mail/i18n/pl.po
odoo/addons/project_task_send_by_mail/i18n/project_task_send_by_mail.pot
odoo/addons/project_task_send_by_mail/i18n/pt.po
odoo/addons/project_task_send_by_mail/i18n/pt_BR.po
odoo/addons/project_task_send_by_mail/i18n/pt_PT.po
odoo/addons/project_task_send_by_mail/i18n/ro.po
odoo/addons/project_task_send_by_mail/i18n/sl.po
odoo/addons/project_task_send_by_mail/i18n/sv.po
odoo/addons/project_task_send_by_mail/i18n/tr.po
odoo/addons/project_task_send_by_mail/i18n/uk.po
odoo/addons/project_task_send_by_mail/i18n/zh_CN.po
odoo/addons/project_task_send_by_mail/models/__init__.py
odoo/addons/project_task_send_by_mail/models/project.py
odoo11_addon_project_task_send_by_mail-11.0.1.0.0.99.dev8.dist-info/METADATA
odoo11_addon_project_task_send_by_mail-11.0.1.0.0.99.dev8.dist-info/WHEEL
odoo11_addon_project_task_send_by_mail-11.0.1.0.0.99.dev8.dist-info/top_level.txt
odoo11_addon_project_task_send_by_mail-11.0.1.0.0.99.dev8.dist-info/RECORD
